linkml_csv/__init__.py
linkml_csv/dumpers/__init__.py
linkml_csv/dumpers/csv_dumper.py
linkml_csv/loaders/__init__.py
linkml_csv/loaders/csv_loader.py
linkml_csv/utils/__init__.py
linkml_csv/utils/converter.py
linkml_csv/utils/csvutils.py
linkml_csv-0.0.4.dist-info/AUTHORS
linkml_csv-0.0.4.dist-info/LICENSE
linkml_csv-0.0.4.dist-info/METADATA
linkml_csv-0.0.4.dist-info/WHEEL
linkml_csv-0.0.4.dist-info/entry_points.txt
linkml_csv-0.0.4.dist-info/pbr.json
linkml_csv-0.0.4.dist-info/top_level.txt
linkml_csv-0.0.4.dist-info/RECORD
